xdmod_data/__init__.py
xdmod_data/__version__.py
xdmod_data/_descriptors.py
xdmod_data/_http_requester.py
xdmod_data/_response_processor.py
xdmod_data/_validator.py
xdmod_data/themes.py
xdmod_data/warehouse.py
xdmod_data-1.0.3.dist-info/LICENSE
xdmod_data-1.0.3.dist-info/METADATA
xdmod_data-1.0.3.dist-info/WHEEL
xdmod_data-1.0.3.dist-info/top_level.txt
xdmod_data-1.0.3.dist-info/RECORD
